mtmimgviewer/QCrossItem.py
mtmimgviewer/QPicView.py
mtmimgviewer/__init__.py
mtmimgviewer/cli.py
mtmimgviewer/logic_main_window.py
mtmimgviewer-1.0.2.dist-info/LICENSE
mtmimgviewer-1.0.2.dist-info/METADATA
mtmimgviewer-1.0.2.dist-info/WHEEL
mtmimgviewer-1.0.2.dist-info/entry_points.txt
mtmimgviewer-1.0.2.dist-info/top_level.txt
mtmimgviewer-1.0.2.dist-info/RECORD
