Metadata-Version: 2.1
Name: mtmimgviewer
Version: 1.0.2
Summary: A simple GUI for viewing images.
License: MIT License
Classifier: Development Status :: 3 - Alpha
Classifier: Programming Language :: Python :: 3.8
Classifier: Intended Audience :: Developers
Classifier: License :: OSI Approved :: Apache Software License
Classifier: Operating System :: MacOS
Classifier: Operating System :: POSIX :: Linux
Classifier: Operating System :: Microsoft :: Windows
Requires-Python: >=3.8
License-File: LICENSE
Requires-Dist: pyside6 >=6.2.0
Requires-Dist: pillow >=8.3.2
